{"dependencies":[{"name":"./main.js","dynamic":true,"parent":"/Users/armenchorbajian/Desktop/YouTubeFinder/index.html","resolved":"/Users/armenchorbajian/Desktop/YouTubeFinder/main.js"}],"generated":{"html":"<!DOCTYPE html>\n<html>\n<head>\n    <meta charset=\"utf-8\">\n    <meta http-equiv=\"X-UA-Compatible\" content=\"IE=edge\">\n    <title>YouTube Channel Finder</title>\n    <meta name=\"viewport\" content=\"width=device-width, initial-scale=1\">\n    <link rel=\"stylesheet\" href=\"https://cdnjs.cloudflare.com/ajax/libs/materialize/1.0.0-rc.2/css/materialize.min.css\">\n\n    <style>\n        #content, \n        #authorize-button, \n        #signout-button {\n            display: none;\n        }\n    </style>\n</head>\n\n<body>\n    <nav class=\"black\">\n        <div class=\"nav-wrapper\">\n            <div class=\"container\">\n                <a href=\"#!\" class=\"brand-logo\">YouTube Channel Finder</a>\n            </div>\n        </div>\n    </nav>\n    <br>\n    <section>\n        <div class=\"container\">\n            <p>Log In With Google</p>\n            <button class=\"btn red\" id=\"authorize-button\">Log In</button>\n            <button class=\"btn red\" id=\"signout-button\">Log Out</button>\n            <br>\n            <div id=\"content\">\n                <div class=\"row\">\n                    <div class=\"col s6\">\n                        <form id=\"channel-form\">\n                            <div class=\"input-field col s8\">\n                                <input type=\"text\" id=\"channel-input\" placeholder=\"Enter Channel Name\">\n                                <input type=\"submit\" value=\"Get Channel Data\" class=\"btn grey\">\n                            </div>\n                        </form>\n                    </div>\n                    <div id=\"channel-data\" class=\"col s6\"></div>\n                </div>\n                <div class=\"row\" id=\"video-container\"></div>\n            </div>\n        </div>\n    </section>\n\n    <script src=\"https://cdnjs.cloudflare.com/ajax/libs/materialize/1.0.0-rc.2/js/materialize.min.js\"></script>\n    <script async=\"\" defer=\"\" src=\"https://apis.google.com/js/api.js\" onload=\"this.onload=function(){};handleClientLoad()\" onreadystatechange=\"if (this.readyState === 'complete') this.onload()\">\n    </script>\n    <script src=\"/24c41bcf4fe87e603f96144d1553bffc.js\"></script>\n</body>\n</html>"},"hash":"7c99c04e85742376090774cbf4d95093","cacheData":{},"id":1}